asyncapi_python/__init__.py
asyncapi_python/amqp/__init__.py
asyncapi_python/amqp/base_application.py
asyncapi_python/amqp/connection.py
asyncapi_python/amqp/endpoint/__init__.py
asyncapi_python/amqp/endpoint/base.py
asyncapi_python/amqp/endpoint/receiver.py
asyncapi_python/amqp/endpoint/sender.py
asyncapi_python/amqp/error.py
asyncapi_python/amqp/operation.py
asyncapi_python/amqp/params.py
asyncapi_python/amqp/utils.py
asyncapi_python/py.typed
asyncapi_python/utils.py
asyncapi_python_codegen/__init__.py
asyncapi_python_codegen/document/__init__.py
asyncapi_python_codegen/document/base.py
asyncapi_python_codegen/document/bindings/__init__.py
asyncapi_python_codegen/document/bindings/amqp.py
asyncapi_python_codegen/document/components.py
asyncapi_python_codegen/document/document.py
asyncapi_python_codegen/document/document_context.py
asyncapi_python_codegen/document/ref.py
asyncapi_python_codegen/document/utils.py
asyncapi_python_codegen/generators/__init__.py
asyncapi_python_codegen/generators/amqp/__init__.py
asyncapi_python_codegen/generators/amqp/generate.py
asyncapi_python_codegen/generators/amqp/templates/__init__.py.j2
asyncapi_python_codegen/generators/amqp/templates/application.py.j2
asyncapi_python_codegen/generators/amqp/templates/routes.py.j2
asyncapi_python_codegen/py.typed
asyncapi_python_pants/__init__.py
asyncapi_python_pants/py.typed
asyncapi_python_pants/register.py
asyncapi_python_pants/rules.py
asyncapi_python_pants/targets.py
asyncapi_python-0.2.5.dist-info/LICENSE
asyncapi_python-0.2.5.dist-info/METADATA
asyncapi_python-0.2.5.dist-info/WHEEL
asyncapi_python-0.2.5.dist-info/entry_points.txt
asyncapi_python-0.2.5.dist-info/RECORD
