Metadata-Version: 2.3
Name: asyncapi-python
Version: 0.2.5
Summary: Easily generate type-safe and async Python applications from AsyncAPI 3 specifications.
License: Apache-2.0
Author: Yaroslav Petrov
Author-email: yaroslav.v.petrov@gmail.com
Requires-Python: >=3.9,<3.14
Classifier: License :: OSI Approved :: Apache Software License
Classifier: Programming Language :: Python :: 3
Classifier: Programming Language :: Python :: 3.9
Classifier: Programming Language :: Python :: 3.10
Classifier: Programming Language :: Python :: 3.11
Classifier: Programming Language :: Python :: 3.12
Classifier: Programming Language :: Python :: 3.13
Provides-Extra: amqp
Provides-Extra: codegen
Requires-Dist: aio-pika ; extra == "amqp"
Requires-Dist: black ; extra == "codegen"
Requires-Dist: datamodel-code-generator[http] (>=0.26.4,<0.27.0) ; extra == "codegen"
Requires-Dist: jinja2 (>=3.1.4,<4.0.0) ; extra == "codegen"
Requires-Dist: pydantic (>=2)
Requires-Dist: pytz
Requires-Dist: pyyaml ; extra == "codegen"
Requires-Dist: typer[all] (>=0.12.5,<0.13.0) ; extra == "codegen"
